LICENSE
README.md
tests/__init__.py
tests/conftest.py
tests/integration/__init__.py
tests/unit/__init__.py
toggl_mcp/__init__.py
toggl_mcp/__main__.py
toggl_mcp/api_params.py
toggl_mcp/main.py
toggl_mcp/toggl_client.py
toggl_mcp-0.1.8.2.dist-info/METADATA
toggl_mcp-0.1.8.2.dist-info/WHEEL
toggl_mcp-0.1.8.2.dist-info/entry_points.txt
toggl_mcp-0.1.8.2.dist-info/licenses/LICENSE
toggl_mcp-0.1.8.2.dist-info/RECORD
